_PyPartMC.cpython-39-darwin.so
PyPartMC/__init__.py
PyPartMC/.dylibs/libgfortran.5.dylib
PyPartMC/.dylibs/libquadmath.0.dylib
PyPartMC/.dylibs/libgcc_s.1.1.dylib
pypartmc-1.7.2.dist-info/RECORD
pypartmc-1.7.2.dist-info/WHEEL
pypartmc-1.7.2.dist-info/top_level.txt
pypartmc-1.7.2.dist-info/METADATA
pypartmc-1.7.2.dist-info/licenses/LICENSE
