Metadata-Version: 2.1
Name: pypartmc
Version: 1.7.2
Summary: Python interface to PartMC
Author: PyPartMC team (see https://github.com/open-atmos/PyPartMC/graphs/contributors)
Author-email: nriemer@illinois.edu
License: GPL-3.0
Project-URL: Tracker, https://github.com/open-atmos/PyPartMC/issues
Project-URL: Documentation, https://open-atmos.github.io/PyPartMC
Project-URL: Source, https://github.com/open-atmos/PyPartMC/
Requires-Python: >=3.7
License-File: LICENSE
Requires-Dist: numpy
Provides-Extra: examples
Requires-Dist: matplotlib !=3.10.0 ; extra == 'examples'
Requires-Dist: ipywidgets ; extra == 'examples'
Requires-Dist: voila ; extra == 'examples'
Requires-Dist: open-atmos-jupyter-utils ; extra == 'examples'
Requires-Dist: PySDM ; extra == 'examples'
Requires-Dist: PyMieScatt ; extra == 'examples'
Requires-Dist: SciPy ; extra == 'examples'
Requires-Dist: dustpy ; (platform_system != "Windows") and extra == 'examples'
Provides-Extra: tests
Requires-Dist: pytest ; extra == 'tests'
Requires-Dist: pytest-order ; extra == 'tests'
Requires-Dist: fastcore !=1.5.8 ; extra == 'tests'
Requires-Dist: ghapi ; extra == 'tests'
Requires-Dist: scipy ; extra == 'tests'
